dataclasses_json_speakeasy/__init__.py
dataclasses_json_speakeasy/__version__.py
dataclasses_json_speakeasy/api.py
dataclasses_json_speakeasy/cfg.py
dataclasses_json_speakeasy/core.py
dataclasses_json_speakeasy/mm.py
dataclasses_json_speakeasy/py.typed
dataclasses_json_speakeasy/stringcase.py
dataclasses_json_speakeasy/undefined.py
dataclasses_json_speakeasy/utils.py
dataclasses_json_speakeasy-0.5.10.dist-info/LICENSE
dataclasses_json_speakeasy-0.5.10.dist-info/METADATA
dataclasses_json_speakeasy-0.5.10.dist-info/WHEEL
dataclasses_json_speakeasy-0.5.10.dist-info/RECORD
