Metadata-Version: 2.1
Name: dataclasses-json-speakeasy
Version: 0.5.10
Summary: Easily serialize dataclasses to and from JSON.
Home-page: https://github.com/speakeasy-api/dataclasses-json
License: MIT
Author: Charles Li
Author-email: charles.dt.li@gmail.com
Maintainer: Charles Li
Maintainer-email: charles.dt.li@gmail.com
Requires-Python: >=3.7,<4.0
Classifier: License :: OSI Approved :: MIT License
Classifier: Programming Language :: Python :: 3
Classifier: Programming Language :: Python :: 3.7
Classifier: Programming Language :: Python :: 3.8
Classifier: Programming Language :: Python :: 3.9
Classifier: Programming Language :: Python :: 3.10
Classifier: Programming Language :: Python :: 3.11
Classifier: Programming Language :: Python :: 3.12
Requires-Dist: marshmallow (>=3.18.0,<4.0.0)
Requires-Dist: typing-inspect (>=0.4.0,<1)
Project-URL: Repository, https://github.com/speakeasy-api/dataclasses-json
Project-URL: changelog, https://github.com/speakeasy-api/dataclasses-json/releases
Project-URL: documentation, https://speakeasy-api.github.io/dataclasses-json/
Project-URL: issues, https://github.com/speakeasy-api/dataclasses-json/issues
